auto_prep/__init__.py
auto_prep/modeling/__init__.py
auto_prep/modeling/handler.py
auto_prep/modeling/model_BayesianRidgeRegressor.py
auto_prep/modeling/model_DecisionTreeClassifier.py
auto_prep/modeling/model_GaussianNaiveClassifier.py
auto_prep/modeling/model_GradientBoostingRegressor.py
auto_prep/modeling/model_KNeighboursClassifier.py
auto_prep/modeling/model_KNeighboursRegressor.py
auto_prep/modeling/model_LinearRegression.py
auto_prep/modeling/model_LinearSVR.py
auto_prep/modeling/model_LogisticRegression.py
auto_prep/modeling/model_RandomForestRegressor.py
auto_prep/modeling/model_SVC.py
auto_prep/modeling/model_XGBoost.py
auto_prep/prep.py
auto_prep/preprocessing/__init__.py
auto_prep/preprocessing/abstract.py
auto_prep/preprocessing/binning.py
auto_prep/preprocessing/correlation_filtering.py
auto_prep/preprocessing/dimention_reducing.py
auto_prep/preprocessing/encoding.py
auto_prep/preprocessing/feature_selecting.py
auto_prep/preprocessing/handler.py
auto_prep/preprocessing/imputing.py
auto_prep/preprocessing/outlier_detecting.py
auto_prep/preprocessing/redundancy_filtering.py
auto_prep/preprocessing/scaling.py
auto_prep/preprocessing/utils.py
auto_prep/preprocessing/variance_filtering.py
auto_prep/raporting/__init__.py
auto_prep/raporting/eda.py
auto_prep/raporting/overview.py
auto_prep/raporting/raport.py
auto_prep/utils/__init__.py
auto_prep/utils/abstract.py
auto_prep/utils/config.py
auto_prep/utils/logging_config.py
auto_prep/utils/other.py
auto_prep/utils/system.py
auto_prep/visualization/__init__.py
auto_prep/visualization/categorical.py
auto_prep/visualization/eda.py
auto_prep/visualization/numerical.py
auto_prep-0.2.3.dist-info/METADATA
auto_prep-0.2.3.dist-info/WHEEL
auto_prep-0.2.3.dist-info/entry_points.txt
auto_prep-0.2.3.dist-info/RECORD
