Metadata-Version: 2.3
Name: auto-prep
Version: 0.2.3
Summary: AutoML with enhanced preprocessing and explainability.
License: GPLv3
Author: Paweł Pozorski
Author-email: pozorski.paul@gmail.com
Requires-Python: >=3.10,<4.0
Classifier: License :: OSI Approved :: GNU General Public License v3 (GPLv3)
Classifier: License :: Other/Proprietary License
Classifier: Operating System :: OS Independent
Classifier: Programming Language :: Python :: 3
Classifier: Programming Language :: Python :: 3.10
Classifier: Programming Language :: Python :: 3.11
Classifier: Programming Language :: Python :: 3.12
Classifier: Programming Language :: Python :: 3.13
Provides-Extra: docs
Requires-Dist: feature-engine (>=1.4.1,<2.0.0)
Requires-Dist: ghp-import (>=2.1.0,<3.0.0)
Requires-Dist: humanize (>=4.11.0,<5.0.0)
Requires-Dist: matplotlib (>=3.8,<3.9)
Requires-Dist: numpy (>=1.23.0,<2.0.0)
Requires-Dist: optuna (>=2.10.0,<3.0.0)
Requires-Dist: pandas (>=1.4.0,<2.0.0)
Requires-Dist: pandas-profiling (>=3.2.0,<4.0.0)
Requires-Dist: pylatex (>=1.4.1,<2.0.0)
Requires-Dist: scikit-learn (>=1.0.2,<2.0.0)
Requires-Dist: seaborn (>=0.11.2,<0.12.0)
Requires-Dist: shap (>=0.46.0,<0.47.0)
Requires-Dist: sphinx (>=8.1.3,<9.0.0) ; extra == "docs"
Requires-Dist: sphinx-rtd-theme (>=3.0.2,<4.0.0) ; extra == "docs"
Requires-Dist: tqdm (>=4.67.1,<5.0.0)
Requires-Dist: umap-learn (>=0.5.7,<0.6.0)
Requires-Dist: xgboost (>=2.1.3,<3.0.0)
Project-URL: Documentation, https://pawlo77.github.io/AutoPrep/
Project-URL: Homepage, https://github.com/Pawlo77/AutoPrep.git
Project-URL: Repository, https://github.com/Pawlo77/AutoPrep.git
